Metadata-Version: 1.0
Name: dsnd-distributions-sk-7
Version: 15.3.2
Summary: Gaussian and Binomial distributions
Home-page: UNKNOWN
Author: UNKNOWN
Author-email: UNKNOWN
License: UNKNOWN
Platform: UNKNOWN
